coconut/__init__.py
coconut/lime.py
coconut/question.py
coconut/response.py
coconut/survey.py
coconut/utils.py
coconut/version.py
coconut/workbook.py
limesurvey_coconut-1.0.1.dist-info/LICENSE.txt
limesurvey_coconut-1.0.1.dist-info/METADATA
limesurvey_coconut-1.0.1.dist-info/WHEEL
limesurvey_coconut-1.0.1.dist-info/top_level.txt
limesurvey_coconut-1.0.1.dist-info/RECORD
