Metadata-Version: 2.1
Name: limesurvey-coconut
Version: 1.0.1
Summary: Coconut - A LimeSurvey data extraction and helper library
Home-page: https://github.com/istresearch/coconut
Author: IST Research
Author-email: support@istresearch.com
License: MIT License
Platform: UNKNOWN
Classifier: Programming Language :: Python :: 3.6
Classifier: Programming Language :: Python :: 3.7
Classifier: Programming Language :: Python :: 3.8
Classifier: License :: OSI Approved :: MIT License
Classifier: Operating System :: OS Independent
Requires-Dist: loguru (>=0.5.1)
Requires-Dist: google-oauth (==1.0.1)
Requires-Dist: gspread-pandas (==2.2.3)
Requires-Dist: pandas (>=1.0.5)
Requires-Dist: tinyrpc (==1.0.4)
Requires-Dist: pendulum (>=2.1.0)
Requires-Dist: pyyaml (>=5.3.1)
Requires-Dist: tqdm (>=4.47.0)
Requires-Dist: xlsxwriter (>=1.2.9)
